{
    "Car": "BUR-474",
    "CarOrigin": "12bur474",
    "Series": "",
    "Title": "\u30ab\u30e9\u30c0\u3092\u58f2\u308b\u7d20\u4eba\u30cf\u30e1\u64ae\u308a\u4e2d\u51fa\u3057\u6d41\u51fa\u6620\u50cf\u96c6 4\u6642\u9593",
    "TitleZh": "\u5356\u8eab\u7684\u5916\u884c\u62cd\u6444\u4e2d\u51fa\u6d41\u51fa\u6620\u50cf\u96c64\u5c0f\u65f6",
    "Plot": "\u30b9\u30b1\u30d9\u3067\u30e4\u30ea\u30de\u30f3\u306a\u7d20\u4eba\u5a18\u305f\u3061\u3068\u306e\u30d7\u30e9\u30a4\u30d9\u30fc\u30c8SEX\u8a18\u9332\u3002\u30cf\u30e1\u64ae\u308a\u3069\u3053\u308d\u304b\u751f\u4e2d\u51fa\u3057\u3082\u62d2\u307e\u306a\u3044\u3001\u904e\u6fc0\u3067\u5351\u7325\u904e\u304e\u308b\u7d20\u4eba10\u4eba\u306e\u75f4\u614b\u304c\u3001\u6295\u7a3f\u30de\u30cb\u30a2\u306b\u3088\u308b\u5973\u306e\u5b50\u672c\u4eba\u7121\u8a31\u53ef\u306e\u6fc0\u30e4\u30d0\u6620\u50cf\u3067\u9732\u306b\u306a\u3063\u3061\u3083\u3046\uff01\uff1f",
    "PlotZh": "\u4e0e\u597d\u8272\u4e14\u4e0d\u505a\u4f5c\u7684\u7d20\u4eba\u5973\u513f\u4eec\u7684\u79c1\u751f\u6d3bSEX\u8bb0\u5f55\u3002\u975e\u4f46\u4e0d\u62cd\u7167\u7247\uff0c\u8fde\u4e2d\u51fa\u90fd\u4e0d\u62d2\u7edd\uff0c\u8fc7\u6fc0\u4e14\u7325\u4eb5\u8fc7\u5934\u768410\u4e2a\u7d20\u4eba\u7684\u75f4\u6001\uff0c\u5728\u6295\u7a3f\u72c2\u7684\u5973\u5b69\u672c\u4eba\u672a\u7ecf\u8bb8\u53ef\u7684\u6fc0\u70c8\u95f9\u5267\u5f71\u50cf\u4e2d\u88ab\u66dd\u5149\u4e86\uff01\uff1f",
    "Review": "",
    "Release": "2016-05-01",
    "Runtime": 240,
    "Director": "",
    "Studio": "\u30b0\u30ec\u30a4\u30ba",
    "Publisher": "BURST\uff08\u30b0\u30ec\u30a4\u30ba\uff09",
    "Score": 0.0,
    "CoverDb": "https://c1.jdbstatic.com/covers/xg/XgybJ.jpg",
    "CoverLibrary": "",
    "CoverBus": "5gzn_b.jpg",
    "CoverDmm": "http://pics.dmm.co.jp/mono/movie/adult/12bur474/12bur474pl.jpg",
    "JavDb": "XgybJ",
    "JavLibrary": "javliljj2u",
    "JavBus": "BUR-474",
    "Arzon": "1331445",
    "Version": "2022-04-26",
    "Genres": [
        "\u4e3b\u89c2\u89c6\u89d2",
        "4\u5c0f\u65f6+",
        "\u6295\u7a3f",
        "\u5de8\u4e73",
        "\u4e1a\u4f59",
        "\u4e2d\u51fa"
    ],
    "Actors": [],
    "Init": "2022-04-04 18:28:19",
    "Modify": "2022-04-22 17:52:26",
    "Crop": "0.52625 1.42",
    "Jav321": "",
    "Cover321": "",
    "Poster": ""
}