{
    "Car": "DSE-689",
    "CarOrigin": "402dse689",
    "Series": "",
    "Title": "\u6deb\u4e71\u719f\u5973\u30d9\u30b9\u30c810 VOL.2",
    "TitleZh": "\u6deb\u4e71\u719f\u5973BEST10 VOL.2",
    "Plot": "\u3010arzon\u6709\u8be5\u5f71\u7247\uff0c\u4f46\u627e\u4e0d\u5230\u7b80\u4ecb\u3011",
    "PlotZh": "",
    "Review": "",
    "Release": "2010-09-29",
    "Runtime": 240,
    "Director": "",
    "Studio": "\u30c9\u30ea\u30fc\u30e0\u30b9\u30c6\u30fc\u30b8",
    "Publisher": "\u719f\u5973\u7d75\u5dfb",
    "Score": 0,
    "CoverDb": "https://c1.jdbstatic.com/covers/ek/eKmmz.jpg",
    "CoverLibrary": "",
    "CoverBus": "",
    "CoverDmm": "http://pics.dmm.co.jp/mono/movie/adult/402dse689/402dse689pl.jpg",
    "Cover321": "",
    "Poster": "",
    "Crop": "0.52625 1.42",
    "JavLibrary": "javlipry4i",
    "JavDb": "eKmmz",
    "JavBus": "",
    "Jav321": "",
    "Arzon": "",
    "Genres": [
        "\u7cbe\u9009\u7efc\u5408",
        "4\u5c0f\u65f6+",
        "\u719f\u5973"
    ],
    "Actors": [
        "\u751f\u7530\u6c99\u7e54",
        "\u611b\u6a39\u308b\u3044",
        "\u5c71\u53e3\u7f8e\u82b1",
        "\u68b6\u539f\u307e\u3086",
        "\u93e1\u9e97\u5b50"
    ],
    "Init": "2022-05-05 18:36:37",
    "Modify": "2022-05-08 13:33:25",
    "Version": "2022-04-26"
}