{
    "Car": "RKI-418",
    "CarOrigin": "rki418",
    "Series": "",
    "Title": "\u30e9\u30c3\u30ad\u30fc\u30b9\u30b1\u30d9 \u7a81\u767a\u6027\u30cf\u30ec\u30f3\u30c1\u75c7\u5019\u7fa4",
    "TitleZh": "\u5e78\u8fd0\u8272\u9b3c\u7a81\u53d1\u6027\u9a9a\u6270\u75c7\u5019\u7fa4",
    "Plot": "\u7a81\u767a\u6027\u30cf\u30ec\u30f3\u30c1\u75c7\u5019\u7fa4\u3068\u306f\u3001\u65e5\u5e38\u7684\u306b\u30a8\u30ed\u3044\u3053\u3068\u304c\u8d77\u3053\u308a\u7d9a\u3051\u308b\u30e9\u30c3\u30ad\u30fc\u30b9\u30b1\u30d9\u306e\u6b63\u5f0f\u540d\u79f0\u3002\u8d05\u6ca2\u3059\u304e\u308b\u30e9\u30c3\u30ad\u30fc\u30b9\u30b1\u30d9SEX\u3067\u6975\u4e0a\u5feb\u697d\u30cf\u30fc\u30ec\u30e0\u3067\u7d76\u9802\u3068\u3089\u3076\u308b\u3002\u7a81\u767a\u6027\u30cf\u30ec\u30f3\u30c1\u75c7\u5019\u7fa4\u306b\u304b\u304b\u308b\u3068\u30a8\u30ed\u304c\u5411\u3053\u3046\u304b\u3089\u3084\u3063\u3066\u304f\u308b\uff01",
    "PlotZh": "\u7a81\u53d1\u6027\u9a9a\u6270\u75c7\u5019\u7fa4\u662f\u65e5\u5e38\u751f\u6d3b\u4e2d\u6301\u7eed\u53d1\u751f\u8272\u60c5\u4e8b\u4ef6\u7684\u5e78\u8fd0\u8272\u9b3c\u7684\u6b63\u5f0f\u540d\u79f0\u3002\u592a\u8fc7\u5962\u4f88\u7684\u5e78\u8fd0\u597d\u8272SEX\uff0c\u4ee5\u6781\u4f73\u7684\u5feb\u4e50\u540e\u5bab\u8fbe\u5230\u9876\u70b9\u3002\u60a3\u7a81\u53d1\u6027\u9a9a\u6270\u75c7\u5019\u7fa4\u7684\u8bdd\uff0c\u8272\u60c5\u5c31\u4f1a\u4ece\u5bf9\u9762\u6765\uff01",
    "Review": "",
    "Release": "2016-07-19",
    "Runtime": 170,
    "Director": "\u771f\u54b2\u5357\u670b",
    "Studio": "ROOKIE",
    "Publisher": "ROOKIE",
    "Score": 50,
    "CoverDb": "https://c1.jdbstatic.com/covers/xo/XO2a.jpg",
    "CoverLibrary": "",
    "CoverBus": "5juw_b.jpg",
    "CoverDmm": "http://pics.dmm.co.jp/mono/movie/adult/rki418/rki418pl.jpg",
    "Cover321": "",
    "Poster": "",
    "Crop": "0.52625 1.42",
    "JavLibrary": "javlilqo6m",
    "JavDb": "XO2a",
    "JavBus": "RKI-418",
    "Jav321": "",
    "Arzon": "1341615",
    "Genres": [
        "\u6ee5\u4ea4",
        "\u7f8e\u5c11\u5973",
        "\u8361\u5987",
        "\u4e2d\u51fa"
    ],
    "Actors": [
        "\u306a\u3064\u3081\u611b\u8389",
        "\u5bae\u4e0b\u83ef\u5948",
        "\u82b1\u54b2\u3044\u3042\u3093",
        "\u85e4\u6ce2\u3055\u3068\u308a"
    ],
    "Init": "2022-04-04 18:29:26",
    "Modify": "2022-05-06 17:09:45",
    "Version": "2022-04-26"
}