{
    "Car": "IBW-418",
    "CarOrigin": "504ibw418z",
    "Series": "",
    "Title": "\u59b9\u91ce\u5916\u8abf\u6559 \u307e\u30861\u25cb\u624d",
    "TitleZh": "\u59b9\u59b9\u91ce\u5916\u8c03\u6559\u9ebb\u53cb1\u25cb\u5c81",
    "Plot": "\u8ca7\u4e73\u306e\u59b9\u30fb\u307e\u3086\u3092\u91ce\u5916\u9732\u51fa\u8abf\u6559\u3002\u4e2d\u25cb\u751f\u306e\u7d42\u308f\u308a\u9803\u304b\u3089\u8abf\u6559\u3092\u59cb\u3081\u3066\u3088\u3046\u3084\u304f\u3053\u3053\u307e\u3067\u547d\u4ee4\u3092\u805e\u304f\u3088\u3046\u306b\u306a\u308a\u307e\u3057\u305f\u3002\u30d1\u30a4\u30d1\u30f3\u306e\u30a2\u30bd\u30b3\u306f\u6fe1\u308c\u3084\u3059\u304f\u4e2d\u51fa\u3057\u3082\u30b4\u30c3\u30af\u30f3\u3082\u9854\u5c04\u3082\u3059\u3079\u3066\u5f93\u9806\u306b\u53d7\u3051\u5165\u308c\u307e\u3059\u3002",
    "PlotZh": "\u5728\u91ce\u5916\u66dd\u5149\u8c03\u6559\u8d2b\u4e73\u7684\u59b9\u59b9\u9ebb\u53cb\u3002\u4ece\u4e2d\u25cb\u751f\u7ed3\u675f\u7684\u65f6\u5019\u5f00\u59cb\u8c03\u6559\uff0c\u7ec8\u4e8e\u542c\u5230\u4e86\u547d\u4ee4\u3002\u83e0\u841d\u7684\u9752\u9cc9\u9c7c\u5bb9\u6613\u6e7f\uff0c\u4e2d\u51fa\u548c\u6208\u514b\u6797\u548c\u989c\u5c04\u90fd\u6309\u987a\u5e8f\u63a5\u53d7\u3002",
    "Review": "",
    "Release": "2013-12-13",
    "Runtime": 120,
    "Director": "",
    "Studio": "I.B.WORKS",
    "Publisher": "I.B.WORKS",
    "Score": 92,
    "CoverDb": "https://c1.jdbstatic.com/covers/bb/bBee.jpg",
    "CoverLibrary": "",
    "CoverBus": "",
    "CoverDmm": "http://pics.dmm.co.jp/mono/movie/adult/504ibw418z/504ibw418zpl.jpg",
    "JavDb": "bBee",
    "JavLibrary": "javlijivtu",
    "JavBus": "",
    "Arzon": "1162530",
    "Version": "2022-04-26",
    "Genres": [
        "\u6237\u5916",
        "\u4e2d\u51fa",
        "\u59d0\u00b7\u59b9",
        "\u8c03\u6559",
        "\u5e73\u80f8"
    ],
    "Actors": [
        "\u307b\u306e\u304b\u307e\u3086"
    ],
    "Init": "2022-04-04 18:28:43",
    "Modify": "2022-04-23 11:23:48",
    "Crop": "0.52625 1.42",
    "Jav321": "",
    "Cover321": "",
    "Poster": ""
}