{
    "Car": "MDS-134",
    "CarOrigin": "61mds134",
    "Series": "",
    "Title": "\u6deb\u4e71\u30d7\u30ea\u30f3\u30bb\u30b9",
    "TitleZh": "\u6deb\u4e71\u516c\u4e3b",
    "Plot": "\u4e45\u3005\u306bAV\u754c\u306b\u73fe\u308c\u305f\u6b63\u7d71\u6d3e\u304a\u5b22\u3055\u307e\u7cfb\u7f8e\u5c11\u5973\uff65\u5e38\u76e4\u685c\u5b50\u3061\u3083\u3093\u306e\u6b63\u4f53\u306f\u3001\u306a\u3093\u3068\u6deb\u4e71\u3067\u5909\u614b\u306e\u30cf\u30ec\u30f3\u30c1\u5a18\u3060\u3063\u305f!?\u300c\u786c\u3044\u30e2\u30ce\u3067\u79c1\u3092\u72c2\u308f\u305b\u3066\u2026\uff01\u300d\u3068\u61c7\u9858\u3057\u3064\u3064\u3001\u3042\u305d\u3053\u3092\u30d9\u30c1\u30e3\u30d9\u30c1\u30e3\u306b\u6fe1\u3089\u3057\u3066\u4e71\u308c\u307e\u304f\u308b\u3002",
    "PlotZh": "\u4e45\u8fdd\u51fa\u73b0\u5728AV\u754c\u7684\u6b63\u7edf\u6d3e\u5927\u5c0f\u59d0\u7cfb\u7f8e\u5c11\u5973\u5e38\u76d8\u6a31\u5b50\u7684\u771f\u9762\u76ee\uff0c\u7adf\u7136\u662f\u6deb\u4e71\u53d8\u6001\u7684\u83b2\u85d5\u5a18\uff01\uff1f\u201c\u7528\u575a\u786c\u7684\u4e1c\u897f\u8ba9\u6211\u75af\u72c2\u2026\uff01\u201d\u4e00\u8fb9\u6073\u6c42\u7740\uff0c\u4e00\u8fb9\u628a\u90a3\u91cc\u5f04\u6e7f\u5f04\u5f97\u4e71\u4e03\u516b\u7cdf\u3002",
    "Review": "",
    "Release": "2003-04-15",
    "Runtime": 120,
    "Director": "",
    "Studio": "\u5b87\u5b99\u4f01\u753b",
    "Publisher": "\u5b87\u5b99\u4f01\u753b",
    "Score": 0.0,
    "CoverDb": "https://c1.jdbstatic.com/covers/kk/kKBWz.jpg",
    "CoverLibrary": "",
    "CoverBus": "",
    "CoverDmm": "http://pics.dmm.co.jp/mono/movie/adult/61mds134/61mds134pl.jpg",
    "JavDb": "kKBWz",
    "JavLibrary": "javlibzfye",
    "JavBus": "",
    "Arzon": "276493",
    "Version": "2022-04-26",
    "Genres": [
        "\u5076\u50cf\u827a\u4eba",
        "\u7f8e\u5c11\u5973"
    ],
    "Actors": [
        "\u5e38\u76e4\u685c\u5b50"
    ],
    "Init": "2022-04-04 18:29:00",
    "Modify": "2022-04-23 15:06:19",
    "Crop": "0.52625 1.42",
    "Jav321": "",
    "Cover321": "",
    "Poster": ""
}