{
    "Car": "RBD-847",
    "CarOrigin": "rbd847",
    "Series": "\u5974\u96b7\u30bd\u30fc\u30d7\u306b\u5815\u3061\u305f\u25cb\u25cb",
    "Title": "\u5974\u96b7\u30bd\u30fc\u30d7\u306b\u5815\u3068\u3055\u308c\u305f\u4eba\u59bb17",
    "TitleZh": "\u5815\u5165\u5974\u96b6\u80a5\u7682\u7684\u4eba\u59bb17",
    "Plot": "\u30b7\u30b9\u30c6\u30e0\u30d0\u30b9\u7dcf\u5408\u30e1\u30fc\u30ab\u30fc\u306e\u95c7\u3002\u6975\u60aa\u975e\u9053\uff01\u793e\u54e1\u306e\u7f8e\u4eba\u59bb\u305f\u3061\u3092\u4f01\u696d\u306e\u30a4\u30e1\u30fc\u30b8\u5e83\u544a\u306e\u30e2\u30c7\u30eb\u306b\u4f7f\u3063\u305f\u5f8c\u3001\u592b\u306b\u306f\u5185\u7dd2\u3067\u63a5\u5f85\u5974\u96b7\u306b\u8abf\u6559\u3001\u30bd\u30fc\u30d7\u5b22\u3068\u3057\u3066\u5f97\u610f\u5148\u306e\u76f8\u624b\u3092\u3055\u305b\u308b\u2026\u65b0\u305f\u306a\u72a0\u7272\u8005\u3068\u306a\u3063\u305f\u82e5\u59bb\u30fb\u745e\u5e0c\u306e\u904b\u547d\u306f\uff01\uff1f",
    "PlotZh": "\u7cfb\u7edf\u603b\u7ebf\u7efc\u5408\u5236\u9020\u5546\u7684\u9ed1\u6697\u3002\u7a77\u51f6\u6781\u6076\uff01\u5c06\u516c\u53f8\u7684\u7f8e\u5973\u59bb\u5b50\u4eec\u4f5c\u4e3a\u4f01\u4e1a\u5f62\u8c61\u5e7f\u544a\u7684\u6a21\u7279\u4f7f\u7528\u540e\uff0c\u5bf9\u4e08\u592b\u4fdd\u5bc6\uff0c\u8ba9\u63a5\u5f85\u5974\u96b6\u8c03\u6559\uff0c\u8ba9\u5979\u4f5c\u4e3a\u80a5\u7682\u5c0f\u59d0\u6210\u4e3a\u5ba2\u6237\u7684\u5bf9\u8c61\u2026\u6210\u4e3a\u65b0\u727a\u7272\u8005\u7684\u65b0\u5a18\u00b7\u745e\u5e0c\u7684\u547d\u8fd0\u662f\uff01\uff1f",
    "Review": "",
    "Release": "2017-07-25",
    "Runtime": 130,
    "Director": "\u5f8c\u624b\u7e1b\u308a",
    "Studio": "Attackers",
    "Publisher": "\u9f8d\u7e1b",
    "Score": 73,
    "CoverDb": "https://c1.jdbstatic.com/covers/zd/zday.jpg",
    "CoverLibrary": "",
    "CoverBus": "62xv_b.jpg",
    "CoverDmm": "http://pics.dmm.co.jp/mono/movie/adult/rbd847/rbd847pl.jpg",
    "Cover321": "",
    "Poster": "",
    "Crop": "0.52625 1.42",
    "JavLibrary": "javlikrw6u",
    "JavDb": "zday",
    "JavBus": "RBD-847",
    "Jav321": "",
    "Arzon": "1405293",
    "Genres": [
        "\u5993\u5973",
        "\u5355\u4f53\u4f5c\u54c1",
        "\u51cc\u8fb1"
    ],
    "Actors": [
        "\u53cb\u7530\u5f69\u4e5f\u9999"
    ],
    "Init": "2022-04-04 18:29:23",
    "Modify": "2022-05-06 11:16:26",
    "Version": "2022-04-26"
}