{
    "Car": "NITR-266",
    "CarOrigin": "49nitr266",
    "Series": "\u7206\u4e73\u30b3\u30b9\u30d7\u30ec\u30a4\u30e4\u30fc\u767a\u60c5\u4e2d\u51fa\u3057\u6deb\u4ea4\u64ae\u5f71",
    "Title": "J\u30ab\u30c3\u30d7\u7206\u4e73\u30b3\u30b9\u30d7\u30ec\u30a4\u30e4\u30fc\u4e2d\u51fa\u3057\u6deb\u4ea4\u64ae\u5f71",
    "TitleZh": "J\u7f69\u676f\u7206\u4e73COSPLAY\u4e2d\u51fa\u6deb\u4ea4\u6444\u5f71",
    "Plot": "1m\u3092\u8d85\u3048\u308bJ\u30ab\u30c3\u30d7\u7206\u4e73\u306e\u8089\u611f\u30dc\u30c7\u30a3\u306b\u3001\u305d\u308c\u3092\u5f37\u8abf\u3059\u308b\u8863\u88c5\u3092\u307e\u3068\u3063\u305f\u30a8\u30ed\u30b3\u30b9\u30d7\u30ec\u30a4\u30e4\u30fc\u3002\u5f7c\u5973\u3092\u56f2\u3080\u7537\u305f\u3061\u3068\u306e\u751f\u30cf\u30e1\u8f2a\u59e6\u3067\u4f53\u4e2d\u3092\u30b6\u30fc\u30e1\u30f3\u307e\u307f\u308c\u3002\u305d\u3093\u306a\u4ed5\u6253\u3061\u306b\u3046\u3063\u3068\u308a\u3068\u3059\u308b\u30c9M\u3063\u3077\u308a\u306b\u6ce8\u76ee\uff01",
    "PlotZh": "\u5728\u8d85\u8fc71\u7c73\u7684J\u7f69\u676f\u7206\u4e73\u7684\u8089\u611f\u8eab\u4f53\u91cc\uff0c\u7a7f\u7740\u5f3a\u8c03\u8fd9\u4e00\u70b9\u7684\u670d\u88c5\u7684\u8272\u60c5cosplayer\u3002\u548c\u56f4\u7740\u5979\u7684\u7537\u4eba\u4eec\u7684\u751fhame\u8f6e\u5978\u6d51\u8eab\u4e0a\u4e0b\u90fd\u662f\u7cbe\u6db2\u3002\u6ce8\u610f\u4e3a\u8fd9\u6837\u7684\u884c\u4e3a\u800c\u9676\u9189\u7684\u6296M\u98ce\u683c\uff01",
    "Review": "",
    "Release": "2016-12-02",
    "Runtime": 130,
    "Director": "BOBO\u6c60\u888b",
    "Studio": "\u30af\u30ea\u30b9\u30bf\u30eb\u6620\u50cf",
    "Publisher": "NITRO",
    "Score": 48,
    "CoverDb": "https://c1.jdbstatic.com/covers/zn/ZNdRP.jpg",
    "CoverLibrary": "",
    "CoverBus": "5sgy_b.jpg",
    "CoverDmm": "http://pics.dmm.co.jp/mono/movie/adult/49nitr266/49nitr266pl.jpg",
    "Cover321": "",
    "Poster": "",
    "Crop": "0.52625 1.42",
    "JavLibrary": "javlil3v3u",
    "JavDb": "ZNdRP",
    "JavBus": "NITR-266",
    "Jav321": "",
    "Arzon": "1364425",
    "Genres": [
        "\u4e2d\u51fa",
        "\u5355\u4f53\u4f5c\u54c1",
        "\u89d2\u8272\u626e\u6f14",
        "\u989c\u5c04",
        "\u8f6e\u5978",
        "\u5de8\u4e73"
    ],
    "Actors": [
        "\u4e5d\u6761\u3055\u3084\u304b"
    ],
    "Init": "2022-04-04 18:29:16",
    "Modify": "2022-05-05 18:14:52",
    "Version": "2022-04-26"
}