{
    "Car": "MCSR-021",
    "CarOrigin": "57mcsr021",
    "Series": "\u4e2d\u51fa\u3057\u4eba\u59bb\u4e0d\u502b\u65c5\u884c",
    "Title": "\u4e2d\u51fa\u3057\u4eba\u59bb\u4e0d\u502b\u65c5\u884c 16",
    "TitleZh": "\u4e2d\u51fa\u4eba\u59bb\u4e0d\u4f26\u65c5\u884c16",
    "Plot": "\u60c5\u7dd2\u3042\u3075\u308c\u308b\u30a8\u30ed\u30b9\u304c\u4eba\u6c17\u306e\u300c\u4e2d\u51fa\u3057\u4eba\u59bb\u4e0d\u502b\u65c5\u884c\u300d\u30b7\u30ea\u30fc\u30ba\u7b2c\uff11\uff16\u5f3e\u3002\u3058\u3063\u3068\u308a\u3068\u30ab\u30e9\u30c0\u3092\u6fe1\u3089\u3057\u60c5\u71b1\u7684\u306b\u60b6\u3048\u308b\u4eba\u59bb\u30fb\u862d\u3055\u3093\u3002\u6027\u6b32\u304c\u89e3\u304d\u653e\u305f\u308c\u3001\u8276\u3084\u304b\u306a\u8089\u4f53\u304c\u307b\u306e\u304b\u306b\u7d05\u304f\u7537\u3092\u8a98\u3046\u305d\u306e\u4e00\u90e8\u59cb\u7d42\u3092\u53ce\u9332\u3002",
    "PlotZh": "\u5145\u6ee1\u60c5\u8da3\u7684\u7231\u6b32\u662f\u4eba\u6c14\u7684\u201c\u4e2d\u51fa\u4eba\u59bb\u4e0d\u4f26\u65c5\u884c\u201d\u7cfb\u5217\u7b2c16\u5f39\u3002\u6e7f\u6f09\u6f09\u5730\u6fe1\u6e7f\u8eab\u4f53\uff0c\u70ed\u60c5\u5730\u82e6\u95f7\u7684\u4eba\u59bb\u00b7\u5170\u3002\u6027\u6b32\u88ab\u89e3\u653e\uff0c\u8273\u4e3d\u7684\u8089\u4f53\u9690\u7ea6\u53d1\u7ea2\u7684\u8bf1\u60d1\u7537\u4eba\u7684\u4e00\u90e8\u5206\u59cb\u7ec8\u5982\u4e00\u3002",
    "Review": "",
    "Release": "2010-05-25",
    "Runtime": 120,
    "Director": "YUMEJI",
    "Studio": "\u30d3\u30c3\u30b0\u30e2\u30fc\u30ab\u30eb",
    "Publisher": "\u30de\u30b9\u30ab\u30c3\u30c8",
    "Score": 62,
    "CoverDb": "https://c1.jdbstatic.com/covers/e2/E2QAQ.jpg",
    "CoverLibrary": "",
    "CoverBus": "2227_b.jpg",
    "CoverDmm": "http://pics.dmm.co.jp/mono/movie/adult/57mcsr021/57mcsr021pl.jpg",
    "JavDb": "E2QAQ",
    "JavLibrary": "javlipjfry",
    "JavBus": "MCSR-021",
    "Arzon": "607718",
    "Version": "2022-04-26",
    "Genres": [
        "\u4e2d\u51fa",
        "\u4eba\u59bb",
        "\u51fa\u8f68",
        "\u5de8\u4e73"
    ],
    "Actors": [
        "\u9ed2\u5d0e\u6f64"
    ],
    "Init": "2022-04-04 18:28:58",
    "Modify": "2022-04-23 14:44:14",
    "Crop": "0.52625 1.42",
    "Jav321": "",
    "Cover321": "",
    "Poster": ""
}