{
    "Car": "DSE-1129",
    "CarOrigin": "402dse1129",
    "Series": "\u8fd1\u89aa\u76f8\u59e6\u6bcd\u306e\u719f\u308c\u305f\u8eab\u4f53",
    "Title": "\u8fd1\u89aa\u76f8\u59e6 \u6bcd\u306e\u719f\u308c\u305f\u8eab\u4f53 \u9ad8\u68a8\u65e5\u548c",
    "TitleZh": "\u8fd1\u4eb2\u76f8\u5978",
    "Plot": "\u3010arzon\u6709\u8be5\u5f71\u7247\uff0c\u4f46\u627e\u4e0d\u5230\u7b80\u4ecb\u3011",
    "PlotZh": "",
    "Review": "",
    "Release": "2013-06-28",
    "Runtime": 90,
    "Director": "",
    "Studio": "\u30c9\u30ea\u30fc\u30e0\u30b9\u30c6\u30fc\u30b8",
    "Publisher": "\u719f\u5973\u7d75\u5dfb",
    "Score": 0,
    "CoverDb": "https://c1.jdbstatic.com/covers/p3/p3n6Z.jpg",
    "CoverLibrary": "",
    "CoverBus": "425x_b.jpg",
    "CoverDmm": "http://pics.dmm.co.jp/mono/movie/adult/402dse1129/402dse1129pl.jpg",
    "Cover321": "",
    "Poster": "",
    "Crop": "0.52625 1.42",
    "JavLibrary": "javlijatte",
    "JavDb": "p3n6Z",
    "JavBus": "DSE-1129",
    "Jav321": "",
    "Arzon": "",
    "Genres": [
        "\u4e08\u6bcd\u5a18",
        "\u5be1\u5987",
        "\u719f\u5973",
        "\u5355\u4f53\u4f5c\u54c1",
        "\u4e71\u4f26",
        "\u5de8\u4e73"
    ],
    "Actors": [
        "\u9ad8\u68a8\u65e5\u548c",
        "\u5009\u7530\u6c5f\u91cc\u5b50"
    ],
    "Init": "2022-05-05 12:17:30",
    "Modify": "2022-05-08 13:18:23",
    "Version": "2022-04-26"
}