{
    "Car": "EKDV-123",
    "CarOrigin": "49ekdv123",
    "Series": "NONSTOPORGASM\u30dd\u30eb\u30c1\u30aa\u30a8\u30f3\u30c9\u30eb\u30d5\u30a3\u30f3",
    "Title": "NON STOP ORGASM \u30dd\u30eb\u30c1\u30aa\u30a8\u30f3\u30c9\u30eb\u30d5\u30a3\u30f3 \u677e\u3059\u307f\u308c \u7d76\u9802\u5674\u5c04",
    "TitleZh": "NON STOP ORGASM\u706b\u7bad\u70ae\u6069\u5fb7\u677e\u679d\u55b7\u5c04\u7edd\u9876",
    "Plot": "\u4eba\u6c17\u5973\u512a\u306e\u30dd\u30eb\u30c1\u30aa\u3092\u8cac\u3081\u307e\u304f\u308b\u30b7\u30ea\u30fc\u30ba\u306b\u3001\u611b\u304f\u308b\u3057\u3044\u7b11\u9854\u3068\u30ca\u30a4\u30b9\u30dc\u30c7\u30a3\u304c\u9b45\u529b\u306e\u677e\u3059\u307f\u308c\u304c\u767b\u5834\u3002\u6027\u611f\u5e2f\u3078\u306e\u91dd\u7078\u3084\u96fb\u6d41\u306a\u3069\u3001\u672a\u4f53\u9a13\u306e\u5feb\u697d\u3067\u9023\u7d9a\u7d76\u9802\u3002\u30de\u25cb\u30b3\u304b\u3089\u6deb\u6c41\u3092\u5674\u5c04\u3057\u307e\u304f\u308a\u3001\u5927\u7d76\u53eb\u3067\u679c\u3066\u308b\u3002",
    "PlotZh": "\u5728\u8d23\u5907\u4eba\u6c14\u5973\u6f14\u5458\u8272\u60c5\u72c2\u7684\u7cfb\u5217\u4e2d\uff0c\u53ef\u7231\u7684\u7b11\u5bb9\u548c\u8eab\u6750\u9b45\u529b\u5341\u8db3\u7684\u677e\u5807\u767b\u573a\u3002\u7ed9\u6027\u611f\u5e26\u7684\u9488\u7078\u548c\u7535\u6d41\u7b49\uff0c\u4ee5\u672a\u4f53\u9a8c\u7684\u5feb\u4e50\u8fde\u7eed\u7edd\u9876\u3002\u4ecema\u25cb\u4e2a\u90a3\u91cc\u4e00\u4e2a\u52b2\u5730\u55b7\u5c04\u6deb\u6c41\uff0c\u5927\u58f0\u75be\u547c\u7ed3\u675f\u3002",
    "Review": "",
    "Release": "2010-09-24",
    "Runtime": 120,
    "Director": "",
    "Studio": "\u30af\u30ea\u30b9\u30bf\u30eb\u6620\u50cf",
    "Publisher": "e-kiss",
    "Score": 0,
    "CoverDb": "https://c1.jdbstatic.com/covers/nw/Nwdgb.jpg",
    "CoverLibrary": "",
    "CoverBus": "2mo1_b.jpg",
    "CoverDmm": "http://pics.dmm.co.jp/mono/movie/adult/49ekdv123/49ekdv123pl.jpg",
    "JavDb": "Nwdgb",
    "JavLibrary": "javlipru7m",
    "JavBus": "EKDV-123",
    "Arzon": "651605",
    "Version": "2022-04-26",
    "Genres": [
        "\u7f9e\u803b",
        "\u62d8\u675f",
        "\u5b50\u5bab\u9888",
        "\u5355\u4f53\u4f5c\u54c1",
        "\u5de8\u4e73"
    ],
    "Actors": [
        "\u677e\u3059\u307f\u308c"
    ],
    "Init": "2022-04-04 18:28:36",
    "Modify": "2022-04-22 23:32:26",
    "Crop": "0.52625 1.42",
    "Jav321": "",
    "Cover321": "",
    "Poster": ""
}