{
    "Car": "MXSPS-650",
    "CarOrigin": "h_068mxsps650",
    "Series": "\u62d8\u675f\u3055\u308c\u8eab\u52d5\u304d\u304c\u53d6\u308c\u306a\u3044\u72b6\u6cc1\u3067\u30d3\u30af\u30d3\u30af\u75d9\u6523\u30a4\u30ad\u3059\u308b\u7d20\u76f4\u306a\u30aa\u30de\u25cf\u30b3",
    "Title": "\u62d8\u675f\u3055\u308c\u305f\u7f8e\u5973\u305f\u3061 5\u4eba 4\u6642\u9593",
    "TitleZh": "\u88ab\u62d8\u675f\u7684\u7f8e\u59735\u4eba4\u5c0f\u65f6",
    "Plot": "\u6b32\u6c42\u4e0d\u6e80\u5973\u6027\u306e\u5fc3\u306e\u4e2d\u306b\u96a0\u3055\u308c\u305f\u201c\u652f\u914d\u3055\u308c\u305f\u3044\u201d\u6b32\u671b\u3092\u6620\u3057\u51fa\u3059\u62d8\u675f\u30d7\u30ec\u30a4\u306e\u30d9\u30b9\u30c8\u7248\u3002\u8eab\u52d5\u304d\u3067\u304d\u306a\u3044\u4e0d\u81ea\u7531\u306a\u4f53\u52e2\u306b\u62d8\u675f\u3057\u3001\u534a\u5f37\u5236\u7684\u306b\u30a4\u30ab\u30bb\u307e\u304f\u308b\uff01\u5236\u5fa1\u4e0d\u80fd\u306e\u6b32\u60c5\u306f\u3001\u3044\u3064\u3057\u304b\u5f7c\u5973\u3092\u5feb\u697d\u306b\u6eba\u308c\u3055\u305b\u2026\u3002",
    "PlotZh": "\u6b32\u6c42\u4e0d\u6ee1\u53cd\u6620\u51fa\u5973\u6027\u5fc3\u4e2d\u9690\u85cf\u7684\u201c\u60f3\u88ab\u652f\u914d\u201d\u6b32\u671b\u7684\u62d8\u675f\u6e38\u620f\u7684\u7cbe\u9009\u7248\u3002\u88ab\u8eab\u4f53\u65e0\u6cd5\u52a8\u5f39\u7684\u4e0d\u81ea\u7531\u59ff\u52bf\u6240\u675f\u7f1a\uff0c\u534a\u5f3a\u5236\u6027\u5730\u62fc\u547d\u5730\u800d\u5e05\uff01\u65e0\u6cd5\u63a7\u5236\u7684\u6b32\u671b\uff0c\u4e0d\u77e5\u4f55\u65f6\u8ba9\u5979\u6c89\u6eba\u4e8e\u5feb\u4e50\u4e4b\u4e2d\u2026\u3002",
    "Review": "",
    "Release": "2020-05-16",
    "Runtime": 240,
    "Director": "",
    "Studio": "\u30de\u30ad\u30b7\u30f3\u30b0",
    "Publisher": "MAXING",
    "Score": 92,
    "CoverDb": "https://c1.jdbstatic.com/covers/m7/M7n0A.jpg",
    "CoverLibrary": "",
    "CoverBus": "7oup_b.jpg",
    "CoverDmm": "http://pics.dmm.co.jp/mono/movie/adult/h_068mxsps650/h_068mxsps650pl.jpg",
    "Cover321": "",
    "Poster": "",
    "Crop": "0.52625 1.42",
    "JavLibrary": "javli6z64q",
    "JavDb": "M7n0A",
    "JavBus": "MXSPS-650",
    "Jav321": "",
    "Arzon": "1569444",
    "Genres": [
        "\u7f8e\u5c11\u5973",
        "\u5185\u8863",
        "\u62d8\u675f",
        "\u7cbe\u9009\u7efc\u5408",
        "4\u5c0f\u65f6+"
    ],
    "Actors": [
        "\u7531\u611b\u53ef\u5948",
        "\u6ce2\u591a\u91ce\u7ed3\u8863",
        "\u5409\u6cfd\u660e\u6b65",
        "\u54b2\u91ce\u306e\u82b1",
        "\u9ed2\u5bae\u3048\u3044\u307f"
    ],
    "Init": "2022-04-04 18:29:12",
    "Modify": "2022-05-05 11:55:05",
    "Version": "2022-04-26"
}