{
    "Car": "SOE-026",
    "CarOrigin": "soe026",
    "Series": "\u30cd\u30c3\u30c8\u30ea\u6fc3\u539a\u30bb\u30c3\u30af\u30b9",
    "Title": "\u30ae\u30ea\u30e2\u30b6 \u30cd\u30c3\u30c8\u30ea\u6fc3\u539a\u30bb\u30c3\u30af\u30b9",
    "TitleZh": "\u5f3a\u70c8\u505a\u7231",
    "Plot": "\u5929\u7136\u30ed\u30ea\u30fc\u30bf\u5a18\u306e\u304f\u308b\u307f\u3072\u306a\u304c\u6fc3\u539a\u306a\uff14\u672c\u756a\u3067\u30cd\u30c3\u30c8\u30ea\u3068\u3057\u305f\uff26\uff35\uff23\uff2b\u3092\u62ab\u9732\u3002\u30ad\u30b9\u597d\u304d\u306a\u3072\u306a\u30c1\u30e3\u30f3\u3001\u30c7\u30a3\u30fc\u30d7\u30ad\u30b9\uff06\u6fc0\u3057\u3044\u8cac\u3081\u3067\u6f6e\u5439\u304d\u3057\u3001\uff33\uff25\uff38\u3067\u306f\u7d50\u5408\u90e8\u304b\u3089\u767d\u6fc1\u6deb\u6c41\u3092\u5782\u3089\u3057\u3066\u60b6\u7d76\u3002\u672a\u7d4c\u9a13\u306e\u5feb\u611f\u306b\u30a6\u30c3\u30c8\u30ea\u3002\u3010\u30bb\u30eb\u7248\u3068\u30ec\u30f3\u30bf\u30eb\u7248\u3067\u306f\u53ce\u9332\u6642\u9593\u304c\u7570\u306a\u3063\u3066\u304a\u308a\u307e\u3059\u3011",
    "PlotZh": "\u5929\u7136\u841d\u8389\u5c11\u5973\u7684\u6838\u6843\u96cf\u513f\u5728\u6b63\u5f0f\u6f14\u51fa\u4e2d\u62ab\u9732\u4e86\u4f5c\u4e3a\u7f51\u7edc\u6b4c\u624b\u7684FUCK\u3002\u559c\u6b22\u63a5\u543b\u7684\u96cfchan\uff0c\u6df1\u543b&\u6fc0\u70c8\u7684\u8d23\u5907\u9cb8\u9c7c\u55b7\u6c34\uff0cSEX\u4ece\u7ed3\u5408\u90e8\u6ef4\u4e0b\u767d\u6d4a\u6deb\u6c41\u82e6\u95f7\u7edd\u4f26\u3002\u5bf9\u6ca1\u6709\u7ecf\u9a8c\u7684\u5feb\u611f\u611f\u5230\u5f88\u5403\u60ca\u3002\u3010\u5355\u5143\u7248\u548c\u79df\u501f\u7248\u7684\u6536\u5f55\u65f6\u95f4\u4e0d\u540c\u3011",
    "Review": "",
    "Release": "2008-07-19",
    "Runtime": 120,
    "Director": "\u611b\u67d3\u77e5\u4e45",
    "Studio": "S1 NO.1 STYLE",
    "Publisher": "S1 NO.1 STYLE",
    "Score": 40,
    "CoverDb": "https://jdbimgs.com/covers/zn/ZNxyJ.jpg",
    "CoverLibrary": "",
    "CoverBus": "1gl2_b.jpg",
    "CoverDmm": "http://pics.dmm.co.jp/mono/movie/adult/soe026/soe026pl.jpg",
    "Cover321": "",
    "Poster": "",
    "Crop": "0.52625 1.42",
    "JavLibrary": "javlicqp6y",
    "JavDb": "ZNxyJ",
    "JavBus": "SOE-026",
    "Jav321": "",
    "Arzon": "475074",
    "Genres": [
        "\u989c\u5c04",
        "\u8584\u9a6c\u8d5b\u514b",
        "\u6f6e\u5439",
        "\u591aP",
        "\u4e73\u6db2"
    ],
    "Actors": [
        "\u674f\u6a39\u7d17\u5948"
    ],
    "Init": "2022-04-04 18:29:35",
    "Modify": "2022-05-07 15:42:02",
    "Version": "2022-04-26"
}