{
    "Car": "JUL-416",
    "CarOrigin": "jul416",
    "Series": "",
    "Title": "\u6696\u51ac \u30cb\u30c3\u30c8\u30bb\u30fc\u30bf\u30fc\u3067\u6c57\u3070\u3080\u7fa9\u6bcd\u3068\u306e\u4e2d\u51fa\u3057\u6027\u4ea4\u3002",
    "TitleZh": "\u4e0e\u56e0\u6696\u51ac\u9488\u7ec7\u6bdb\u8863\u800c\u6c57\u6d41\u6d43\u80cc\u7684\u7ee7\u6bcd\u7684\u4e2d\u51fa\u6027\u4ea4\u3002",
    "Plot": "\u30cb\u30c3\u30c8\u30bb\u30fc\u30bf\u30fc\u3092\u7740\u305f\u7fa9\u6bcd\u306e\u611b\u4e03\u304c\u3001\u6c57\u3092\u6d6e\u304b\u3079\u3066\u90e8\u5c4b\u306e\u6383\u9664\u3092\u3057\u3066\u3044\u305f\u3002\u3074\u3063\u305f\u308a\u3057\u305f\u30cb\u30c3\u30c8\u304b\u3089\u80f8\u3092\u7a81\u304d\u51fa\u3057\u3001\u8107\u3084\u9996\u7b4b\u306b\u6c57\u3092\u6d6e\u304b\u3079\u3066\u2026\u3002\u305d\u3093\u306a\u7fa9\u6bcd\u306e\u59ff\u306b\u606f\u5b50\u306f\u62b1\u3044\u3066\u3044\u305f\u611f\u60c5\u3092\u6291\u3048\u5207\u308c\u306a\u304f\u306a\u3063\u3066\u2026\u3002",
    "PlotZh": "\u7a7f\u7740\u9488\u7ec7\u6bdb\u8863\u7684\u7ee7\u6bcd\u7231\u4e03\u5192\u7740\u6c57\u6253\u626b\u623f\u95f4\u3002\u4ece\u5408\u8eab\u7684\u9488\u7ec7\u886b\u4e0a\u7a81\u51fa\u80f8\u90e8\uff0c\u814b\u4e0b\u548c\u8116\u5b50\u4e0a\u5192\u7740\u6c57\u2026\u3002\u513f\u5b50\u65e0\u6cd5\u6291\u5236\u7ee7\u6bcd\u62b1\u7740\u7684\u611f\u60c5\u2026\u3002",
    "Review": "",
    "Release": "2020-12-25",
    "Runtime": 120,
    "Director": "\u3072\u3080\u308d\u3063\u304f",
    "Studio": "\u30de\u30c9\u30f3\u30ca",
    "Publisher": "Madonna",
    "Score": 85,
    "CoverDb": "https://c0.jdbstatic.com/covers/bj/BJ6Md.jpg",
    "CoverLibrary": "",
    "CoverBus": "806h_b.jpg",
    "CoverDmm": "http://pics.dmm.co.jp/mono/movie/adult/jul416/jul416pl.jpg",
    "Cover321": "",
    "Poster": "",
    "Crop": "0.52625 1.42",
    "JavLibrary": "javmezly7i",
    "JavDb": "BJ6Md",
    "JavBus": "JUL-416",
    "Jav321": "",
    "Arzon": "1600424",
    "Genres": [
        "\u6570\u4f4d\u9a6c\u8d5b\u514b",
        "\u6d41\u6c57",
        "\u5de8\u4e73",
        "\u719f\u5973",
        "\u4e2d\u51fa",
        "DMM\u72ec\u5bb6",
        "\u5355\u4f53\u4f5c\u54c1",
        "\u4eba\u59bb"
    ],
    "Actors": [
        "\u65b0\u5ddd\u611b\u4e03"
    ],
    "Init": "2022-05-20 09:32:11",
    "Modify": "2022-05-20 09:32:25",
    "Version": "2022-04-26"
}