{
    "Car": "DOKS-481",
    "CarOrigin": "h_139doks481",
    "Series": "",
    "Title": "\u631f\u307e\u308c\u3066W\u63a5\u543b",
    "TitleZh": "\u88ab\u5939\u5728\u4e2d\u95f4W\u63a5\u543b",
    "Plot": "\u4e8c\u4eba\u306e\u5973\u6027\u306b\u631f\u307e\u308c\u3066\u3001\u4ea4\u4e92\u306b\u6fc3\u539a\u63a5\u543b\u3055\u308c\u308b\u6700\u9ad8\u306e\u81f3\u798f\u30d7\u30ec\u30a4\uff01\uff01\u63a5\u543b\u624b\u30b3\u30ad\u3068\u63a5\u543b\u30d5\u30a7\u30e9\u3067\u5c04\u7cbe\u3078\u3068\u5c0e\u3044\u3066\u304f\u308c\u308b\u63a5\u543b\u5feb\u697d\u5929\u56fd\uff01\uff01\u8276\u3081\u304b\u3057\u3044\u820c\u306e\u3046\u306d\u308a\u3092\u3001\u8d85\u9ad8\u753b\u8cea\u30ab\u30e1\u30e9\u306b\u3066\u3058\u3063\u304f\u308a\u3068\u64ae\u5f71\u3057\u307e\u3057\u305f\uff01",
    "PlotZh": "\u3010\u767e\u5ea6\u7ffb\u8bd1\u51fa\u9519\u3011\u4e8c\u4eba\u306e\u5973\u6027\u306b\u631f\u307e\u308c\u3066\u3001\u4ea4\u4e92\u306b\u6fc3\u539a\u63a5\u543b\u3055\u308c\u308b\u6700\u9ad8\u306e\u81f3\u798f\u30d7\u30ec\u30a4\uff01\uff01\u63a5\u543b\u624b\u30b3\u30ad\u3068\u63a5\u543b\u30d5\u30a7\u30e9\u3067\u5c04\u7cbe\u3078\u3068\u5c0e\u3044\u3066\u304f\u308c\u308b\u63a5\u543b\u5feb\u697d\u5929\u56fd\uff01\uff01\u8276\u3081\u304b\u3057\u3044\u820c\u306e\u3046\u306d\u308a\u3092\u3001\u8d85\u9ad8\u753b\u8cea\u30ab\u30e1\u30e9\u306b\u3066\u3058\u3063\u304f\u308a\u3068\u64ae\u5f71\u3057\u307e\u3057\u305f\uff01",
    "Review": "",
    "Release": "2019-05-01",
    "Runtime": 110,
    "Director": "\u6c5a\u4e38",
    "Studio": "OFFICE K\u2019S",
    "Publisher": "OFFICE K\u2019S",
    "Score": 73,
    "CoverDb": "https://c1.jdbstatic.com/covers/ry/RYykg.jpg",
    "CoverLibrary": "",
    "CoverBus": "74cx_b.jpg",
    "CoverDmm": "http://pics.dmm.co.jp/mono/movie/adult/h_139doks481/h_139doks481pl.jpg",
    "JavDb": "RYykg",
    "JavLibrary": "javli7zerq",
    "JavBus": "DOKS-481",
    "Arzon": "1512770",
    "Version": "2022-04-26",
    "Genres": [
        "\u719f\u5973",
        "\u8361\u5987",
        "\u59d0\u59d0",
        "\u6253\u624b\u67aa",
        "\u53e3\u4ea4",
        "\u63a5\u543b"
    ],
    "Actors": [
        "\u7fd4\u7530\u5343\u91cc",
        "\u897f\u7530\u30ab\u30ea\u30ca",
        "\u9ed2\u6728\u3044\u304f\u307f",
        "\u660e\u91cc\u3068\u3082\u304b",
        "\u9999\u82d7\u30ec\u30ce\u30f3",
        "\u798f\u5c71\u7f8e\u4f73",
        "\u85e4\u672c\u7406\u7396",
        "\u5800\u4e95\u306f\u308b\u304b"
    ],
    "Init": "2022-04-04 18:28:28",
    "Modify": "2022-04-22 20:04:14",
    "Crop": "0.52625 1.42",
    "Jav321": "",
    "Cover321": "",
    "Poster": ""
}