{
    "Car": "HBAD-529",
    "CarOrigin": "1hbad529",
    "Series": "",
    "Title": "\u606f\u5b50\u306e\u53cb\u9054\u306e\u30de\u30bb\u30ac\u30ad\u5171\u306b\u6027\u51e6\u7406\u3055\u305b\u3089\u308c\u30b6\u30fc\u30e1\u30f3\u307e\u307f\u308c\u306e\u6bcd\u89aa \uff5e",
    "TitleZh": "\u513f\u5b50\u7684\u670b\u53cb\u7684\u660e\u4fe1\u7247\u90fd\u662f\u88ab\u6027\u5904\u7406\u7684\u6cbe\u6ee1\u4e86\u7cbe\u6db2\u7684\u6bcd\u4eb2\uff5e",
    "Plot": "\u30b7\u30f3\u30b0\u30eb\u30de\u30b6\u30fc\u30fb\u304b\u304a\u308a\u306f\u4ed5\u4e8b\u304c\u5fd9\u3057\u304f\u3001\u5185\u6c17\u306a\u606f\u5b50\u304c\u5fc3\u914d\u3060\u3063\u305f\u3002\u3042\u308b\u65e5\u3001\u606f\u5b50\u304c\u53cb\u3060\u3061\u3092\u5bb6\u306b\u9023\u308c\u3066\u304f\u308b\u304c\u3001\u5f7c\u3089\u306f\u30a8\u30ed\u30de\u30bb\u30ac\u30ad\u3067\u3001\u304b\u304a\u308a\u306f\u6027\u51e6\u7406\u9053\u5177\u306b\u3055\u308c\u3066\u3057\u307e\u3046\u3002\u7f9e\u6065\u30d7\u30ec\u30a4\u306e\u672b\u306b\u9023\u7d9a\u4e2d\u51fa\u3057\uff01",
    "PlotZh": "\u5355\u8eab\u5988\u5988\u9999\u7ec7\u5de5\u4f5c\u5f88\u5fd9\uff0c\u62c5\u5fc3\u5185\u5411\u7684\u513f\u5b50\u3002\u6709\u4e00\u5929\uff0c\u513f\u5b50\u628a\u670b\u53cb\u5e26\u56de\u5bb6\uff0c\u4f46\u662f\u4ed6\u4eec\u662f\u5de5\u53e3\u660e\u4fe1\u7247\uff0c\u9999\u7ec7\u88ab\u5f53\u505a\u4e86\u6027\u5904\u7406\u9053\u5177\u3002\u7f9e\u803b\u6e38\u620f\u7684\u6700\u540e\u8fde\u7eed\u4e2d\u51fa\uff01",
    "Review": "",
    "Release": "2020-03-26",
    "Runtime": 119,
    "Director": "\u30c9\u30e9\u30b4\u30f3\u897f\u5ddd",
    "Studio": "\u30d2\u30d3\u30ce",
    "Publisher": "BABE",
    "Score": 75,
    "CoverDb": "https://c1.jdbstatic.com/covers/5b/5bd5Y.jpg",
    "CoverLibrary": "",
    "CoverBus": "7mdm_b.jpg",
    "CoverDmm": "http://pics.dmm.co.jp/mono/movie/adult/1hbad529/1hbad529pl.jpg",
    "JavDb": "5bd5Y",
    "JavLibrary": "javli63g7q",
    "JavBus": "HBAD-529",
    "Arzon": "1561770",
    "Version": "2022-04-26",
    "Genres": [
        "\u5de8\u4e73",
        "\u5355\u4f53\u4f5c\u54c1",
        "\u5267\u60c5"
    ],
    "Actors": [
        "\u672c\u591a\u304b\u304a\u308a"
    ],
    "Init": "2022-04-04 18:28:40",
    "Modify": "2022-04-23 10:49:52",
    "Crop": "0.52625 1.42",
    "Jav321": "",
    "Cover321": "",
    "Poster": ""
}