{
    "Car": "DASD-172",
    "CarOrigin": "dasd172",
    "Series": "",
    "Title": "\u5c3b\u59e6 \u521d\u30a2\u30ca\u30eb\u30d5\u30a1\u30c3\u30af",
    "TitleZh": "\u4e71\u4f26\u5c0f\u8bf4",
    "Plot": "\u9042\u306b\u30a2\u30ca\u30eb\u30bb\u30c3\u30af\u30b9\u89e3\u7981\uff01\u30de\u30f3\u30b3\u3088\u308a\u3082\uff11\uff10\uff10\u500d\u6c17\u6301\u3061\u826f\u3044\u30a2\u30ca\u30eb\u30a2\u30af\u30e1\u3067\u7d76\u9802\u4e2d\u51fa\u3057\uff01\u30b1\u30c4\u7a74\u3092\u62e1\u5f35\u30fb\u9053\u5177\u8cac\u3081\u3067\u51cc\u8fb1\u3057\u521d\u30a2\u30ca\u30eb\u30bb\u30c3\u30af\u30b9\u3001\u521d\uff12\u7a74\u30b5\u30f3\u30c9\u30a4\u30c3\u30c1\u306e\u521d\u3081\u3066\u5c3d\u304f\u3057\u306e\u300c\u5c3b\u59e6\u300d\u304c\u6e80\u3092\u6301\u3057\u3066\u521d\u767b\u5834\uff01",
    "PlotZh": "\u7ec8\u4e8e\u89e3\u9664\u809b\u95e8\u6027\u7231\uff01\u7528\u6bd4manko\u5fc3\u60c5\u597d100\u500d\u7684\u809b\u95e8\u963f\u514b\u7c73\u7edd\u9876\u4e2d\u51fa\uff01\u7b2c\u4e00\u6b21\u809b\u95e8\u505a\u7231\uff0c\u7b2c\u4e00\u6b21\u4e24\u4e2a\u6d1e\u4e09\u660e\u6cbb\u7b2c\u4e00\u6b21\u5c3d\u5168\u529b\u7684\u201c\u5f3a\u5978\u5c41\u80a1\u201d\uff0c\u4ee5\u6269\u5145\u9053\u5177\u6765\u51cc\u8fb1\u809b\u95e8\u5b54\uff01",
    "Review": "",
    "Release": "2012-02-25",
    "Runtime": 150,
    "Director": "TAKE-D",
    "Studio": "\u30c0\u30b9\u30c3\uff01",
    "Publisher": "\u30c0\u30b9\u30c3\uff01",
    "Score": 90,
    "CoverDb": "https://c1.jdbstatic.com/covers/xw/XWZnP.jpg",
    "CoverLibrary": "",
    "CoverBus": "24j1_b.jpg",
    "CoverDmm": "http://pics.dmm.co.jp/mono/movie/adult/dasd172/dasd172pl.jpg",
    "JavDb": "XWZnP",
    "JavLibrary": "javliodc3q",
    "JavBus": "DASD-172",
    "Arzon": "986777",
    "Version": "2022-04-26",
    "Genres": [
        "\u6ee5\u4ea4",
        "\u7f8e\u81c0",
        "\u809b\u4ea4",
        "\u4e2d\u51fa",
        "\u7f8e\u4e73"
    ],
    "Actors": [
        "\u77e2\u5439\u674f"
    ],
    "Init": "2022-04-04 18:28:26",
    "Modify": "2022-04-22 19:46:14",
    "Crop": "0.52625 1.42",
    "Jav321": "",
    "Cover321": "",
    "Poster": ""
}