{
    "Car": "SNIS-077",
    "CarOrigin": "87",
    "Series": "\u6700\u5f8c\u3067\u6700\u9ad8\u306e\u30a4\u30ab\u30bb\u6280\u3001\u5168\u90e8\u898b\u305b\u307e\u3059\u3002",
    "Title": "\u307b\u3057\u306e\u3042\u3059\u304bFINAL 4\u672c\u756a\u00d74\u6642\u9593\u30b9\u30da\u30b7\u30e3\u30eb",
    "TitleZh": "\u3010\u767e\u5ea6\u7ffb\u8bd1\u51fa\u9519\u3011\u307b\u3057\u306e\u3042\u3059\u304bFINAL 4\u672c\u756a\u00d74\u6642\u9593\u30b9\u30da\u30b7\u30e3\u30eb",
    "Plot": "\u3010\u5f71\u7247\u4e0b\u67b6\uff0c\u6682\u65e0\u7b80\u4ecb\u3011",
    "PlotZh": "",
    "Review": "",
    "Release": "2014-01-19",
    "Runtime": 240,
    "Director": "\u611b\u67d3\u77e5\u4e45",
    "Studio": "S1 NO.1 STYLE",
    "Publisher": "S1 NO.1 STYLE",
    "Score": 83,
    "CoverDb": "https://c1.jdbstatic.com/covers/8d/8dvK.jpg",
    "CoverLibrary": "https://img10.pixhost.to/images/87/43620232_i227542.jpg",
    "CoverBus": "438c_b.jpg",
    "CoverDmm": "",
    "JavDb": "8dvK",
    "JavLibrary": "javlijl7se",
    "JavBus": "SNIS-077",
    "Arzon": "",
    "Version": "2022-04-26",
    "Genres": [
        "\u5355\u4f53\u4f5c\u54c1",
        "\u989c\u5c04",
        "\u7f8e\u5c11\u5973",
        "\u8584\u9a6c\u8d5b\u514b",
        "\u65e0\u7801\u7834\u89e3",
        "\u841d\u8389",
        "\u6f6e\u5439"
    ],
    "Actors": [
        "\u307b\u3057\u306e\u3042\u3059\u304b"
    ],
    "Init": "2022-04-04 18:29:33",
    "Modify": "2022-04-23 17:42:55",
    "Crop": "0.52625 1.42",
    "Jav321": "",
    "Cover321": "",
    "Poster": ""
}