{
    "Car": "CESD-423",
    "CarOrigin": "cesd423",
    "Series": "\u25cb\u25cb\u304c\u30a2\u30ca\u30bf\u306e\u30bb\u30f3\u30ba\u30ea\u5b8c\u5168\u30b5\u30dd\u30fc\u30c8\uff01",
    "Title": "\u685c\u4e95\u5f69\u304c\u30a2\u30ca\u30bf\u306e\u30bb\u30f3\u30ba\u30ea\u5b8c\u5168\u30b5\u30dd\u30fc\u30c8\uff01",
    "TitleZh": "\u6a31\u4e95\u5f69\u5b8c\u5168\u652f\u6301\u4f60\uff01",
    "Plot": "\u685c\u4e95\u5f69\u304c\u30a2\u30ca\u30bf\u306e\u30bb\u30f3\u30ba\u30ea\u3092\u30b5\u30dd\u30fc\u30c8\uff01\u6311\u767a\u8996\u7dda\u3067\u30aa\u30ca\u30cb\u30fc\u3092\u898b\u305b\u4ed8\u3051\u3001\u6deb\u8a9e\u56c1\u304f\u4e3b\u89b3\u30d1\u30a4\u30ba\u30ea\u3068\u9b3c\u30b3\u30ad\u3002\u30d5\u30a7\u30e9\u30c1\u30aa\u63a5\u5199\u3001\u73a9\u5177\u3067\u30a4\u30ad\u307e\u304f\u308a\u3001\u30b9\u30b1\u30d9\u306a\u30bf\u30de\u5438\u3044\u30d5\u30a7\u30e9\u3092\u898b\u305b\u3001\u30d0\u30c3\u30af\u3068\u9a0e\u4e57\u4f4d\u3067\u7a81\u304b\u308c\u307e\u304f\u308b\uff01",
    "PlotZh": "\u6a31\u4e95\u5f69\u652f\u6301\u4f60\u7684\u654f\u611f\u5ea6\uff01\u7528\u6311\u8845\u7684\u89c6\u7ebf\u663e\u793a\u624b\u6deb\uff0c\u6deb\u8bed\u79c1\u8bed\u7684\u4e3b\u89c2pizuri\u548c\u9b3ckoki\u3002\u53e3\u4ea4\u8fd1\u62cd\uff0c\u7528\u73a9\u5177iki\u4e00\u4e2a\u52b2\u5730\uff0c\u663e\u51fa\u597d\u8272\u7684\u7403\u5438\u53e3\u4ea4\uff0c\u4ee5\u80cc\u90e8\u548c\u9a91\u7684\u9a6c\u4f4d\u88ab\u649e\u4e00\u4e2a\u52b2\u5730\uff01",
    "Review": "",
    "Release": "2017-08-13",
    "Runtime": 138,
    "Director": "\u67ca\u708e\u821e",
    "Studio": "\u30bb\u30ec\u30d6\u306e\u53cb",
    "Publisher": "\u30bb\u30ec\u30d6\u306e\u53cb",
    "Score": 78,
    "CoverDb": "https://c1.jdbstatic.com/covers/82/82yJd.jpg",
    "CoverLibrary": "",
    "CoverBus": "64w0_b.jpg",
    "CoverDmm": "http://pics.dmm.co.jp/mono/movie/adult/cesd423/cesd423pl.jpg",
    "JavDb": "82yJd",
    "JavLibrary": "javlikqzs4",
    "JavBus": "CESD-423",
    "Arzon": "1410586",
    "Version": "2022-04-26",
    "Genres": [
        "\u719f\u5973",
        "\u4e3b\u89c2\u89c6\u89d2",
        "\u5355\u4f53\u4f5c\u54c1",
        "\u6deb\u4e71\u771f\u5b9e",
        "\u653e\u5c3f",
        "\u4e73\u4ea4"
    ],
    "Actors": [
        "\u6a31\u4e95\u5f69"
    ],
    "Init": "2022-04-04 18:28:21",
    "Modify": "2022-04-22 18:37:51",
    "Crop": "0.52625 1.42",
    "Jav321": "",
    "Cover321": "",
    "Poster": ""
}