{
    "Car": "EDD-176",
    "CarOrigin": "118edd176",
    "Series": "\u30a8\u30b9\u30ab\u30ec\u30fc\u30c8\u3059\u308b\u30c9\u3057\u308d\u30fc\u3068\u5a18",
    "Title": "\u30a8\u30b9\u30ab\u30ec\u30fc\u30c8\u3059\u308b\u30c9\u3057\u308d\u30fc\u3068\u5a18 176",
    "TitleZh": "\u5347\u7ea7\u7248\u7684\u5973\u4ec6176",
    "Plot": "\u7d20\u4eba\u5a18\u306e\u6deb\u884c\u304c\u30a8\u30b9\u30ab\u30ec\u30fc\u30c8\u3057\u3066\u3001\u60f3\u50cf\u3092\u7d76\u3059\u308b\u75f4\u614b\u3092\u7e70\u308a\u5e83\u3052\u308b\u4eba\u6c17\u30b7\u30ea\u30fc\u30ba\u7b2c176\u5f3e\u3002\u30a2\u30a4\u30c9\u30eb\u7cfb\u306e\u30eb\u30c3\u30af\u30b9\u304c\u582a\u3089\u306a\u3044\u30a2\u30a4\u30ea\u30f3\u3061\u3083\u3093\u3002\u30c7\u30fc\u30c8\u3067\u306f\u5b50\u4f9b\u307f\u305f\u3044\u306b\u306f\u3057\u3083\u3044\u3067\u3044\u305f\u304c\u3001\u30d9\u30c3\u30c9\u306e\u4e0a\u3067\u306f\u2026\u3002",
    "PlotZh": "\u5916\u884c\u5973\u513f\u7684\u6deb\u884c\u5347\u7ea7\uff0c\u5c55\u5f00\u8d85\u4e4e\u60f3\u8c61\u7684\u75f4\u6001\u7684\u4eba\u6c14\u7cfb\u5217\u7b2c176\u5f39\u3002\u5076\u50cf\u7cfb\u7684\u5bb9\u8c8c\u8ba9\u4eba\u65e0\u6cd5\u5fcd\u53d7\u7684\u7231\u73b2\u9171\u3002\u7ea6\u4f1a\u65f6\u50cf\u5b69\u5b50\u4e00\u6837\u6b22\u95f9\uff0c\u4f46\u5728\u5e8a\u4e0a\u2026\u3002",
    "Review": "",
    "Release": "2010-04-01",
    "Runtime": 120,
    "Director": "",
    "Studio": "\u30d7\u30ec\u30b9\u30c6\u30fc\u30b8",
    "Publisher": "\u3060\u307e\u3057\u3084",
    "Score": 0,
    "CoverDb": "https://c1.jdbstatic.com/covers/3z/3Z0a.jpg",
    "CoverLibrary": "",
    "CoverBus": "1pr5_b.jpg",
    "CoverDmm": "http://pics.dmm.co.jp/mono/movie/adult/118edd176/118edd176pl.jpg",
    "Cover321": "",
    "Crop": "0.52625 1.42",
    "JavDb": "3Z0a",
    "JavLibrary": "javlipi66e",
    "JavBus": "EDD-176",
    "Jav321": "",
    "Arzon": "607743",
    "Genres": [
        "\u8fc7\u819d\u889c",
        "\u82d7\u6761",
        "\u653e\u5c3f",
        "\u53ca\u819d\u889c",
        "\u4e1a\u4f59"
    ],
    "Actors": [
        "\u5800\u5185\u611b\u68a8"
    ],
    "Init": "2022-04-20 23:37:46",
    "Modify": "2022-04-24 14:16:41",
    "Version": "2022-04-26",
    "Poster": ""
}