{
    "Car": "SAMA-199",
    "CarOrigin": "h_244sama199",
    "Series": "\u521d\u3081\u3066\u306eAV\u51fa\u6f14\u3002",
    "Title": "\u521d\u3081\u3066\u306eAV\u51fa\u6f14\u3002 4",
    "TitleZh": "\u7b2c\u4e00\u6b21\u51fa\u6f14AV\u30024",
    "Plot": "\u7d20\u4eba\u306e\u521d\u3081\u3066\u306eAV\u51fa\u6f14\u3092\u6349\u3048\u305f\u30b7\u30ea\u30fc\u30ba\u7b2c4\u5f3e\u3002\u6975\u4e0a\u30dc\u30c7\u30a3\u304c\u305d\u305d\u308b\u308a\u3055\u3061\u3083\u3093\u3002\u30de\u30ea\u30f3\u30b7\u30e7\u30c3\u30d7\u3067\u50cd\u3044\u3066\u3044\u308b\u3068\u3044\u3046\u5f7c\u5973\u306e\u63c9\u307f\u5fdc\u3048\u306e\u3042\u308b\u30d0\u30b9\u30c8\u306b\u5f15\u304d\u7de0\u307e\u3063\u305f\u30a6\u30a8\u30b9\u30c8\uff06\u30d2\u30c3\u30d7\u3092\u582a\u80fd\u3057\u3061\u3083\u3044\u307e\u3059\uff01",
    "PlotZh": "\u6293\u4f4f\u4e86\u5916\u884c\u7684\u7b2c\u4e00\u6b21\u7684AV\u6f14\u51fa\u7684\u7cfb\u5217\u7b2c4\u5b50\u5f39\u3002\u6781\u4e0a\u8eab\u6750\u52fe\u8d77\u7684\u308a\u3055\u9171\u3002\u5728Marine shop\u5de5\u4f5c\u7684\u5979\uff0c\u53ef\u4ee5\u4eab\u53d7\u5230\u4e30\u6ee1\u7684\u80f8\u56f4\u548c\u81c0\u90e8\uff01",
    "Review": "",
    "Release": "2010-01-15",
    "Runtime": 120,
    "Director": "",
    "Studio": "S\u7d1a\u7d20\u4eba",
    "Publisher": "S\u7d1a\u7d20\u4eba",
    "Score": 0.0,
    "CoverDb": "https://c1.jdbstatic.com/covers/wq/WQA5R.jpg",
    "CoverLibrary": "",
    "CoverBus": "11ue_b.jpg",
    "CoverDmm": "http://pics.dmm.co.jp/mono/movie/adult/h_244sama199/h_244sama199pl.jpg",
    "JavDb": "WQA5R",
    "JavLibrary": "javlipao64",
    "JavBus": "SAMA-199",
    "Arzon": "550767",
    "Version": "2022-04-26",
    "Genres": [
        "\u4e3b\u89c2\u89c6\u89d2",
        "\u7f8e\u5c11\u5973",
        "\u591aP",
        "\u4e1a\u4f59",
        "\u7f8e\u4e73",
        "\u6df1\u5589"
    ],
    "Actors": [],
    "Init": "2022-04-04 18:29:28",
    "Modify": "2022-04-23 16:16:02",
    "Crop": "0.52625 1.42",
    "Jav321": "",
    "Cover321": "",
    "Poster": ""
}