{
    "Car": "NNPJ-035",
    "CarOrigin": "nnpj035",
    "Series": "\u30ca\u30f3\u30d1JAPANEXPRESS",
    "Title": "31\u6b73\u53ef\u611b\u3059\u304e\u308bG\u30ab\u30c3\u30d7\u4eba\u59bb \u661f\u91ce\u7f8e\u54b2AV\u30c7\u30d3\u30e5\u30fc \u30ca\u30f3\u30d1JAPAN EXPRESS Vol.09",
    "TitleZh": "31\u5c81\u8d85\u53ef\u7231\u7684G\u7f69\u676f\u4eba\u59bb\u661f\u91ce\u7f8e\u54b2AV\u51fa\u9053\u642d\u8baaJAPAN EXPRESS Vol.09",
    "Plot": "\u898b\u305f\u76ee\u304c\u30bf\u30a4\u30d7\u3067\u30ca\u30f3\u30d1\u3057\u305f\u5b50\u306f\uff13\uff11\u6b73\u306e\u4eba\u59bb\u3067\u3057\u305f\u3002\u5143\u3054\u5f53\u5730\u30df\u30b9\u30b3\u30f3\u306e\u5f7c\u5973\u306f\u5357\u56fd\u3067\u4e00\u4eba\u65c5\u3092\u3057\u3066\u3044\u307e\u3057\u305f\u3002\uff13\u6b73\u306e\u5b50\u6301\u3061\u82e5\u59bb\u306f\u65e6\u90a3\u306b\u5185\u7dd2\u3067\uff21\uff36\u51fa\u6f14\u3092\u6c7a\u5fc3\u3057\u3001\u4ed6\u4eba\u306e\u8089\u68d2\u3067\u4f55\u5ea6\u3082\u7d76\u9802\u3057\u3061\u3083\u3044\u307e\u3059\u3002\u6700\u5f8c\u306f\u4e2d\u51fa\u3057\uff01",
    "PlotZh": "\u5916\u8868\u662f\u7c7b\u578b\u7684\u642d\u8baa\u7684\u5b69\u5b50\u662f31\u5c81\u7684\u4eba\u59bb\u3002\u539f\u672c\u5730\u9009\u7f8e\u6bd4\u8d5b\u7684\u5979\u72ec\u81ea\u4e00\u4eba\u5728\u5357\u56fd\u65c5\u884c\u30023\u5c81\u7684\u6709\u5b69\u5b50\u7684\u5e74\u8f7b\u59bb\u5b50\u5bf9\u4e08\u592b\u79d8\u5bc6\u51b3\u5b9aAV\u6f14\u51fa\uff0c\u7528\u522b\u4eba\u7684\u8089\u68d2\u591a\u6b21\u7edd\u9876\u3002\u6700\u540e\u662f\u4e2d\u51fa\uff01",
    "Review": "",
    "Release": "2014-07-25",
    "Runtime": 120,
    "Director": "",
    "Studio": "\u30ca\u30f3\u30d1JAPAN",
    "Publisher": "\u30ca\u30f3\u30d1JAPAN",
    "Score": 75,
    "CoverDb": "https://c1.jdbstatic.com/covers/v4/V47KQ.jpg",
    "CoverLibrary": "",
    "CoverBus": "4cuk_b.jpg",
    "CoverDmm": "http://pics.dmm.co.jp/mono/movie/adult/nnpj035/nnpj035pl.jpg",
    "Cover321": "",
    "Poster": "",
    "Crop": "0.52625 1.42",
    "JavLibrary": "javlijzxyu",
    "JavDb": "V47KQ",
    "JavBus": "NNPJ-035",
    "Jav321": "",
    "Arzon": "1208596",
    "Genres": [
        "\u4e2d\u51fa",
        "\u9996\u6b21\u4eae\u76f8",
        "\u5355\u4f53\u4f5c\u54c1",
        "\u4eba\u59bb",
        "\u5de8\u4e73",
        "\u730e\u8273"
    ],
    "Actors": [
        "\u6d45\u898b\u305b\u308a"
    ],
    "Init": "2022-04-04 18:29:16",
    "Modify": "2022-05-05 18:52:36",
    "Version": "2022-04-26"
}