{
    "Car": "MILD-564",
    "CarOrigin": "84mild564",
    "Series": "",
    "Title": "\u5f15\u9000\uff01\u30d1\u30a4\u30d1\u30f3\u3068\u30a2\u30ca\u30eb\u8cac\u3081\u306b\u6311\u6226\uff01",
    "TitleZh": "\u5f15\u9000\uff01\u6311\u6218\u83e0\u841d\u548c\u809b\u95e8\u8d23\u5907\uff01",
    "Plot": "\u300c\u666e\u901a\u306e\u5973\u306e\u5b50\u306b\u623b\u308a\u307e\u3059\u300d\u3068\u5ba3\u8a00\u3057\u3001\u6f6e\u5439\u304d\u30af\u30a4\u30fc\u30f3\u30fb\u6d45\u5c3e\u30ea\u30ab\u304c\u5f15\u9000\uff01\u5f7c\u5973\u304c\u6700\u5f8c\u306b\u6311\u3080\u306e\u306f\u30d1\u30a4\u30d1\u30f3\uff06\u30a2\u30ca\u30eb\u3002\u5243\u6bdb\u306b\u6065\u3089\u3046\u59ff\u304b\u3089\u30a2\u30ca\u30eb\uff33\uff25\uff38\u306b\u60b6\u7d76\u3059\u308b\u59ff\u307e\u3067\u3001\u5f7c\u5973\u306e\u52c7\u59ff\u3092\u3057\u3063\u304b\u308a\u76ee\u306b\u713c\u304d\u4ed8\u3051\u3088\uff01",
    "PlotZh": "\u5ba3\u8a00\u201c\u6211\u8981\u56de\u5230\u666e\u901a\u7684\u5973\u5b69\u5b50\u8eab\u4e0a\u201d\uff0c\u6f6e\u5439\u5973\u738b\u6d45\u5c3e\u5229\u4f73\u5f15\u9000\uff01\u5979\u6700\u540e\u6311\u6218\u7684\u662f\u83e0\u841d\u548c\u809b\u95e8\u3002\u4ece\u5bf9\u5243\u6bdb\u5bb3\u7f9e\u7684\u8eab\u59ff\u5230\u5bf9\u809b\u95e8SEX\u82e6\u95f7\u7684\u8eab\u59ff\uff0c\u597d\u597d\u5730\u5728\u773c\u4e0a\u70d9\u4e0a\u5979\u7684\u52c7\u59ff\u5427\uff01",
    "Review": "",
    "Release": "2008-09-19",
    "Runtime": 120,
    "Director": "",
    "Studio": "\u30b1\u30a4\u30fb\u30a8\u30e0\u30fb\u30d7\u30ed\u30c7\u30e5\u30fc\u30b9",
    "Publisher": "million",
    "Score": 0,
    "CoverDb": "https://c1.jdbstatic.com/covers/r3/r3zyJ.jpg",
    "CoverLibrary": "",
    "CoverBus": "",
    "CoverDmm": "http://pics.dmm.co.jp/mono/movie/adult/84mild564/84mild564pl.jpg",
    "Cover321": "",
    "Poster": "",
    "Crop": "0.52625 1.42",
    "JavLibrary": "javlimlcsi",
    "JavDb": "r3zyJ",
    "JavBus": "",
    "Jav321": "",
    "Arzon": "478732",
    "Genres": [
        "\u6f6e\u5439",
        "\u4e2d\u51fa",
        "\u65e0\u6bdb",
        "\u809b\u4ea4"
    ],
    "Actors": [
        "\u6d45\u5c3e\u30ea\u30ab"
    ],
    "Init": "2022-04-04 18:29:09",
    "Modify": "2022-05-05 09:02:04",
    "Version": "2022-04-26"
}