{
    "Car": "MILD-444",
    "CarOrigin": "84mild444",
    "Series": "",
    "Title": "\u6027\u611f\u958b\u767a\uff01\uff01\u6f6e\u5439\u304d\u7279\u8a13 \u677e\u7530\u4e9c\u7f8e \u5b8c\u5168\u7248",
    "TitleZh": "\u6027\u611f\u5f00\u53d1\uff01\uff01\u6f6e\u5439\u7279\u8bad\u677e\u7530\u4e9a\u7f8e\u5b8c\u5168\u7248",
    "Plot": "\u3010arzon\u6709\u8be5\u5f71\u7247\uff0c\u4f46\u627e\u4e0d\u5230\u7b80\u4ecb\u3011",
    "PlotZh": "",
    "Review": "",
    "Release": "2006-11-17",
    "Runtime": 120,
    "Director": "KINGDOM",
    "Studio": "\u30b1\u30a4\u30fb\u30a8\u30e0\u30fb\u30d7\u30ed\u30c7\u30e5\u30fc\u30b9",
    "Publisher": "million",
    "Score": 0,
    "CoverDb": "https://c1.jdbstatic.com/covers/o2/O2BWK.jpg",
    "CoverLibrary": "",
    "CoverBus": "",
    "CoverDmm": "http://pics.dmm.co.jp/mono/movie/adult/84mild444/84mild444pl.jpg",
    "Cover321": "",
    "Poster": "",
    "Crop": "0.52625 1.42",
    "JavLibrary": "javlidtd3u",
    "JavDb": "O2BWK",
    "JavBus": "",
    "Jav321": "",
    "Arzon": "",
    "Genres": [
        "\u6f6e\u5439",
        "\u989c\u5c04",
        "\u9a91\u4e58",
        "\u63d2\u5165\u624b\u6307"
    ],
    "Actors": [
        "\u677e\u7530\u4e9c\u7f8e"
    ],
    "Init": "2022-04-04 18:29:09",
    "Modify": "2022-05-05 08:50:30",
    "Version": "2022-04-26"
}