{
    "Car": "MIBD-813",
    "CarOrigin": "mibd813",
    "Series": "",
    "Title": "\u8131\u304c\u3055\u305a\u633f\u5165\uff01\u30d1\u30f3\u30c4\u305a\u3089\u3057\u30cf\u30e1",
    "TitleZh": "\u4e0d\u8131\u5730\u63d2\u5165\uff01\u5c0f\u88e4\u88e4",
    "Plot": "\u30d1\u30f3\u30c4\u3092\u8131\u304c\u3055\u306a\u3044\u307b\u3046\u304c\u30a8\u30ed\u3044\u3068\u611f\u3058\u3066\u3044\u308b\u30a2\u30ca\u30bf\uff01\u30d1\u30f3\u30c4\u3092\u305a\u3089\u3057\u3066\u3001\u6fe1\u308c\u305f\u30a2\u30bd\u30b3\u306b\u633f\u5165\u3059\u308b\u300c\u30d1\u30f3\u30c4\u305a\u3089\u3057\u30cf\u30e1\u300d\u3092\u305f\u3063\u3077\u308a\u53ce\u9332\u3057\u307e\u3057\u305f\uff01\u30d0\u30c3\u30af\u304b\u3089\u306f\u3082\u3061\u308d\u3093\u3001\u6b63\u5e38\u4f4d\u3001\u9a0e\u4e57\u4f4d\u3067\u30d1\u30f3\u30c4\u3092\u305a\u3089\u3057\u305f\u307e\u307e\u30cf\u30e1\u308b\u30bb\u30c3\u30af\u30b9\u3092\u3054\u582a\u80fd\u304f\u3060\u3055\u3044\uff01",
    "PlotZh": "\u4e0d\u8131\u5185\u88e4\u66f4\u6027\u611f\u7684\u4f60\uff01\u9519\u5f00\u88e4\u88c5\uff0c\u5145\u5206\u6536\u5f55\u4e86\u63d2\u5165\u88ab\u6dcb\u6e7f\u7684\u809a\u8110\u88d9\u4e2d\u7684\u201c\u4e0d\u7a7f\u5185\u88e4\u7684hame\u201d\uff01\u4ece\u80cc\u90e8\u5f00\u59cb\u5c31\u4e0d\u7528\u8bf4\u4e86\uff0c\u8bf7\u4eab\u53d7\u6b63\u5e38\u4f4d\uff0c\u5728\u9a91\u4e58\u4f4d\u4e0a\u9519\u5f00\u5185\u88e4\u7684\u505a\u7231\u5427\uff01",
    "Review": "",
    "Release": "2014-04-13",
    "Runtime": 240,
    "Director": "",
    "Studio": "MOODYZ",
    "Publisher": "MOODYZ Best",
    "Score": 0,
    "CoverDb": "https://c1.jdbstatic.com/covers/aj/AJxm.jpg",
    "CoverLibrary": "",
    "CoverBus": "47a5_b.jpg",
    "CoverDmm": "http://pics.dmm.co.jp/mono/movie/adult/mibd813/mibd813pl.jpg",
    "Cover321": "",
    "Poster": "",
    "Crop": "0.52625 1.42",
    "JavLibrary": "javlijrv6u",
    "JavDb": "AJxm",
    "JavBus": "MIBD-813",
    "Jav321": "",
    "Arzon": "1188183",
    "Genres": [
        "\u604b\u7269\u7656",
        "\u5185\u8863",
        "\u5404\u79cd\u804c\u4e1a",
        "\u7cbe\u9009\u7efc\u5408",
        "\u6570\u4f4d\u9a6c\u8d5b\u514b"
    ],
    "Actors": [
        "JULIA",
        "\u897f\u5c3e\u304b\u304a\u308a",
        "\u4f50\u85e4\u9065\u5e0c",
        "\u307f\u306a\u305b\u512a\u590f",
        "\u3064\u307c\u307f",
        "\u6c34\u57ce\u5948\u7eea",
        "\u9577\u8c37\u5ddd\u30ea\u30db",
        "\u4ed3\u591a\u771f\u592e",
        "\u9752\u6728\u7f8e\u7a7a",
        "\u5009\u6728\u3072\u306a"
    ],
    "Init": "2022-04-04 18:29:06",
    "Modify": "2022-05-04 20:34:27",
    "Version": "2022-04-26"
}