{
    "Car": "WANZ-897",
    "CarOrigin": "wanz897",
    "Series": "",
    "Title": "\u30cf\u30c3\u30b9\u30eb\u30bf\u30a4\u30e0\u306f\u7121\u5236\u9650\u4e2d\u51fa\u3057\uff01\uff01 \u3053\u3063\u305d\u308a\u88cf\u30aa\u30d7\u5168\u958b\u304a\u3063\u30d1\u30d6\u5b22 \u672c\u756aOK\u30d1\u30a4\u30ba\u30ea\u3054\u5949\u4ed5\u30d1\u30d5\u30d1\u30d5\u5929\u56fd\u30d5\u30eb\u30b3\u30fc\u30b9",
    "TitleZh": "\u65e0\u9650\u5236\u4e2d\u51fa\uff01\uff01\u79d8\u5bc6\u5168\u5f00\u7684\u9152\u5427\u5c0f\u59d0\u6b63\u5f0f\u8868\u6f14OK\u4e3a\u88c1\u7f1d\u670d\u52a1\u5e15\u592b\u5df4\u592b\u5929\u56fd\u5168\u5957\u5957\u9910",
    "Plot": "\u304a\u3063\u30d1\u30d6\u5b22\u306eI\u30ab\u30c3\u30d7\u7206\u67d4\u4e73\u3092\u63c9\u307f\u30fb\u5438\u3044\u3001\u9023\u7d9a\u4e2d\u51fa\u3057\uff01\u30b4\u30ad\u30b2\u30f3\u304a\u3063\u30d1\u30d6\u5b22\u306e\u307e\u3064\u308a\u3061\u3083\u3093\u304c\u3001\u88cf\u30aa\u30d7\u306e\u8d85\u904e\u6fc0\u30b5\u30fc\u30d3\u30b9\u3092\u7e70\u308a\u51fa\u3059\u3002\u304a\u3063\u3071\u3044\u5bc6\u7740\u9a0e\u4e57\u4f4d\u30d4\u30b9\u30c8\u30f3SEX\u3001\u306d\u3063\u3068\u308a\u4e73\u9996\u30a4\u30b8\u308a\u5c0f\u60aa\u9b54SEX\uff01",
    "PlotZh": "\u6309\u6469\u00b7\u5438\u542e\u8001\u677f\u5a18\u7684I\u7f69\u676f\u7206\u67d4\u4e73\uff0c\u8fde\u7eed\u4e2d\u51fa\uff01\u54e5\u5409\u6839\u5927\u9152\u5e97\u7684\u5973\u513f\u8282\uff0c\u63a8\u51fa\u4e86\u8d85\u8fc7\u6fc0\u7684\u670d\u52a1\u3002\u7d27\u8d34\u4e73\u623f\u9a91\u4e58\u4f4d\u6d3b\u585eSEX\uff0c\u7c98\u7cca\u7cca\u5730\u4e73\u5934\u51cc\u4e71\u5c0f\u6076\u9b54SEX\uff01",
    "Review": "",
    "Release": "2019-10-01",
    "Runtime": 170,
    "Director": "",
    "Studio": "\u30ef\u30f3\u30ba\u30d5\u30a1\u30af\u30c8\u30ea\u30fc",
    "Publisher": "WANZ FACTORY",
    "Score": 92,
    "CoverDb": "https://c1.jdbstatic.com/covers/ab/aBe73.jpg",
    "CoverLibrary": "",
    "CoverBus": "7ar8_b.jpg",
    "CoverDmm": "http://pics.dmm.co.jp/mono/movie/adult/wanz897/wanz897pl.jpg",
    "Cover321": "",
    "Poster": "",
    "Crop": "0.52625 1.42",
    "JavLibrary": "javli6lhzu",
    "JavDb": "aBe73",
    "JavBus": "WANZ-897",
    "Jav321": "",
    "Arzon": "1535001",
    "Genres": [
        "\u5355\u4f53\u4f5c\u54c1",
        "\u5993\u5973",
        "\u4e2d\u51fa",
        "\u4e73\u4ea4",
        "\u5de8\u4e73",
        "\u9a91\u4e58",
        "\u793c\u4eea\u5c0f\u59d0"
    ],
    "Actors": [
        "\u6850\u8c37\u307e\u3064\u308a"
    ],
    "Init": "2022-04-04 18:35:32",
    "Modify": "2022-05-07 07:16:31",
    "Version": "2022-04-26"
}