{
    "Car": "NITR-235",
    "CarOrigin": "49nitr235",
    "Series": "",
    "Title": "\u771f\u9762\u76ee\u30c9M\u30c7\u30ab\u5c3bOL\u306e\u5909\u614b\u30a2\u30ca\u30eb\u4ea4\u5c3e",
    "TitleZh": "\u8ba4\u771f\u7684M\u5927\u5c41\u80a1OL\u7684\u53d8\u6001\u809b\u95e8\u4ea4\u5c3e",
    "Plot": "\u300c\u81ea\u5206\u306f\u30c9M\u3067\u5909\u614b\u300d\u3068\u544a\u767d\u3059\u308b\u771f\u9762\u76ee\u305d\u3046\u306a\u7ae5\u9854OL\u304b\u3089\u5c4a\u3044\u305f\u3001AV\u51fa\u6f14\u5e0c\u671b\u306e\u30e1\u30fc\u30eb\u306b\u8208\u5473\u3092\u6301\u3063\u305f\u30b9\u30bf\u30c3\u30d5\u3002\u30a4\u30f3\u30bf\u30d3\u30e5\u30fc\u304b\u3089\u5909\u614b\u767a\u8a00\u3092\u9023\u767a\u3059\u308b\u5f7c\u5973\u306b\u306f\u9060\u616e\u306f\u7121\u7528\u3068\u3070\u304b\u308a\u306b\u3001\u30cf\u30fc\u30c9\u306a\u30d7\u30ec\u30a4\u3092\u9023\u767a\uff01",
    "PlotZh": "\u5de5\u4f5c\u4eba\u5458\u5bf9\u201c\u6211\u662f\u6296M\u53d8\u6001\u201d\u544a\u767d\u7684\u7ae5\u989cOL\u53d1\u6765\u7684\u5e0c\u671b\u51fa\u6f14AV\u7684\u90ae\u4ef6\u5f88\u611f\u5174\u8da3\u3002\u5bf9\u4ece\u91c7\u8bbf\u8fde\u7eed\u53d1\u51fa\u53d8\u6001\u53d1\u8a00\u7684\u5979\u6765\u8bf4\u662f\u4e0d\u9700\u8981\u5ba2\u6c14\u7684\uff0c\u8fde\u7eed\u6253\u4e86\u5f88\u591a\u786c\u7684\u6e38\u620f\uff01",
    "Review": "",
    "Release": "2016-07-22",
    "Runtime": 150,
    "Director": "Buddha D",
    "Studio": "\u30af\u30ea\u30b9\u30bf\u30eb\u6620\u50cf",
    "Publisher": "NITRO",
    "Score": 78,
    "CoverDb": "https://c1.jdbstatic.com/covers/rd/RdWMn.jpg",
    "CoverLibrary": "",
    "CoverBus": "5l8n_b.jpg",
    "CoverDmm": "http://pics.dmm.co.jp/mono/movie/adult/49nitr235/49nitr235pl.jpg",
    "Cover321": "",
    "Poster": "",
    "Crop": "0.52625 1.42",
    "JavLibrary": "javlilq53e",
    "JavDb": "RdWMn",
    "JavBus": "NITR-235",
    "Jav321": "",
    "Arzon": "1340123",
    "Genres": [
        "\u809b\u4ea4",
        "\u5355\u4f53\u4f5c\u54c1",
        "\u541e\u7cbe",
        "\u5de8\u5c3b",
        "\u6346\u7ed1",
        "\u704c\u80a0",
        "\u6237\u5916"
    ],
    "Actors": [
        "\u6a2a\u5c3e\u54b2\u5e0c"
    ],
    "Init": "2022-04-04 18:29:16",
    "Modify": "2022-05-05 18:12:46",
    "Version": "2022-04-26"
}